product_hunt_mcp/__init__.py
product_hunt_mcp/cli.py
product_hunt_mcp/api/__init__.py
product_hunt_mcp/api/client.py
product_hunt_mcp/api/queries.py
product_hunt_mcp/schemas/__init__.py
product_hunt_mcp/schemas/validation.py
product_hunt_mcp/tools/__init__.py
product_hunt_mcp/tools/collections.py
product_hunt_mcp/tools/comments.py
product_hunt_mcp/tools/posts.py
product_hunt_mcp/tools/server.py
product_hunt_mcp/tools/topics.py
product_hunt_mcp/tools/users.py
product_hunt_mcp/utils/__init__.py
product_hunt_mcp/utils/common.py
product_hunt_mcp/utils/rate_limit.py
product_hunt_mcp/utils/token.py
product_hunt_mcp/utils/validation.py
product_hunt_mcp-0.1.0.dist-info/METADATA
product_hunt_mcp-0.1.0.dist-info/WHEEL
product_hunt_mcp-0.1.0.dist-info/entry_points.txt
product_hunt_mcp-0.1.0.dist-info/RECORD
