Metadata-Version: 2.4
Name: product-hunt-mcp
Version: 0.1.0
Summary: Product Hunt MCP Server - A FastMCP implementation for the Product Hunt API
Project-URL: Homepage, https://github.com/jaipandya/producthunt-mcp-server
Project-URL: Bug Tracker, https://github.com/jaipandya/producthunt-mcp-server/issues
Project-URL: Documentation, https://github.com/jaipandya/producthunt-mcp-server#readme
Author: Jai Pandya
License: MIT
Keywords: ai,api,fastmcp,mcp,product-hunt
Classifier: Development Status :: 5 - Production/Stable
Classifier: Intended Audience :: Developers
Classifier: License :: OSI Approved :: MIT License
Classifier: Programming Language :: Python :: 3
Classifier: Programming Language :: Python :: 3.10
Classifier: Programming Language :: Python :: 3.11
Classifier: Programming Language :: Python :: 3.12
Classifier: Topic :: Software Development :: Libraries :: Python Modules
Requires-Python: >=3.10
Requires-Dist: fastmcp>=0.3.0
Requires-Dist: requests>=2.31.0
Provides-Extra: dev
Requires-Dist: black>=23.0.0; extra == 'dev'
Requires-Dist: ruff>=0.0.270; extra == 'dev'
